cfn_review_bot/__init__.py
cfn_review_bot/__main__.py
cfn_review_bot/_version.py
cfn_review_bot/aws.py
cfn_review_bot/canonical.py
cfn_review_bot/cfn.py
cfn_review_bot/dirloader.py
cfn_review_bot/error.py
cfn_review_bot/loader.py
cfn_review_bot/main.py
cfn_review_bot/markdown.py
cfn_review_bot/merge.py
cfn_review_bot/model.py
cfn_review_bot/package-version.json
cfn_review_bot/test_merge.py
cfn_review_bot/schema/__init__.py
cfn_review_bot/schema/aws.py
cfn_review_bot/schema/stack.py
cfn_review_bot/schema/target.py
cfn_review_bot/schema/template.py
cfn_review_bot/schema/test_stack.py
cfn_review_bot/schema/util.py
cfn_review_bot/templates/summary.md
cfn_review_bot-1!20240507.22909.data/data/requirements/requirements.txt
cfn_review_bot-1!20240507.22909.dist-info/LICENSE
cfn_review_bot-1!20240507.22909.dist-info/METADATA
cfn_review_bot-1!20240507.22909.dist-info/WHEEL
cfn_review_bot-1!20240507.22909.dist-info/entry_points.txt
cfn_review_bot-1!20240507.22909.dist-info/top_level.txt
cfn_review_bot-1!20240507.22909.dist-info/RECORD
